e3smlab/__init__.py
e3smlab/__main__.py
e3smlab/e3smtimestat.py
e3smlab/inspectcompile.py
e3smlab/kgcompiler.py
e3smlab/main.py
e3smlab/nml2json.py
e3smlab/pacedb.py
e3smlab/pacedbnml.py
e3smlab/pacedbtbl.py
e3smlab-0.3.7.dist-info/LICENSE
e3smlab-0.3.7.dist-info/METADATA
e3smlab-0.3.7.dist-info/WHEEL
e3smlab-0.3.7.dist-info/entry_points.txt
e3smlab-0.3.7.dist-info/top_level.txt
e3smlab-0.3.7.dist-info/RECORD
